{
  "school": "LIGHTNING",
  "range": 48,
  "cast": {
    "duration": 0.5,
    "animation": "spell_engine:one_handed_projectile_charge",
    "sound": {
      "id": "spell_engine:generic_lightning_casting",
      "randomness": 0
    },
    "particles": [
      {
        "particle_id": "spell_engine:electric_arc_a",
        "shape": "PIPE",
        "origin": "FEET",
        "count": 1.0,
        "min_speed": 0.06,
        "max_speed": 0.12
      },
      {
        "particle_id": "spell_engine:electric_arc_b",
        "shape": "PIPE",
        "origin": "FEET",
        "count": 1.0,
        "min_speed": 0.06,
        "max_speed": 0.12
      }
    ]
  },
  "release": {
    "target": {
      "type": "CURSOR",
      "cursor": {
        "use_caster_as_fallback": false
      }
    },
    "animation": "spell_engine:one_handed_projectile_release",
    "sound": {
      "id": "spell_engine:generic_lightning_release"
    }
  },
  "impact": [
    {
      "action": {
        "type": "DAMAGE",
        "damage": {
          "spell_power_coefficient": 0
        }
      }
    }
  ],
  "cost": {
    "cooldown_duration": 3.0,
    "exhaust": 0.2
  }
}